ModularCirc/HelperRoutines.py
ModularCirc/Solver.py
ModularCirc/StateVariable.py
ModularCirc/Time.py
ModularCirc/_BatchRunner.py
ModularCirc/__init__.py
ModularCirc/Analysis/BaseAnalysis.py
ModularCirc/Analysis/__init__.py
ModularCirc/Components/ComponentBase.py
ModularCirc/Components/HC_constant_elastance.py
ModularCirc/Components/HC_mixed_elastance.py
ModularCirc/Components/HC_mixed_elastance_pp.py
ModularCirc/Components/R_component.py
ModularCirc/Components/Rc_component.py
ModularCirc/Components/Rlc_component.py
ModularCirc/Components/Valve_maynard.py
ModularCirc/Components/Valve_non_ideal.py
ModularCirc/Components/Valve_simple_bernoulli.py
ModularCirc/Components/__init__.py
ModularCirc/Models/KorakianitisMixedModel.py
ModularCirc/Models/KorakianitisMixedModelPP.py
ModularCirc/Models/KorakianitisMixedModel_parameters.py
ModularCirc/Models/NaghaviModel.py
ModularCirc/Models/NaghaviModelParameters.py
ModularCirc/Models/OdeModel.py
ModularCirc/Models/ParametersObject.py
ModularCirc/Models/__init__.py
modularcirc-0.3.0.dist-info/licenses/LICENSE
modularcirc-0.3.0.dist-info/METADATA
modularcirc-0.3.0.dist-info/WHEEL
modularcirc-0.3.0.dist-info/top_level.txt
modularcirc-0.3.0.dist-info/RECORD
