Metadata-Version: 2.4
Name: ModularCirc
Version: 0.3.0
Summary: A python package for creating and running 0D models of the cardiovascular system
Author-email: Maximilian Balmus <mbalmus@turing.ac.uk>
License-Expression: MIT
Project-URL: Homepage, https://github.com/alan-turing-institute/ModularCirc
Project-URL: Source Code, https://github.com/alan-turing-institute/ModularCirc
Project-URL: Bug Tracker, https://github.com/alan-turing-institute/ModularCirc/issues
Requires-Python: >=3.10
License-File: LICENSE
Requires-Dist: matplotlib
Requires-Dist: numba
Requires-Dist: numpy
Requires-Dist: pandas
Requires-Dist: scipy
Requires-Dist: joblib
Requires-Dist: pandera
Requires-Dist: tdqm
Provides-Extra: notebooks
Requires-Dist: ipykernel; extra == "notebooks"
Provides-Extra: dev
Requires-Dist: pre-commit; extra == "dev"
Requires-Dist: black; extra == "dev"
Requires-Dist: flake8; extra == "dev"
Requires-Dist: isort; extra == "dev"
Dynamic: license-file
